AUTHORS.rst
HISTORY.rst
LICENSE
MANIFEST.in
README.rst
setup.cfg
setup.py
stf_selector/__init__.py
stf_selector/query.py
stf_selector/selector.py
stf_selector/stf.py
stf_selector.egg-info/PKG-INFO
stf_selector.egg-info/SOURCES.txt
stf_selector.egg-info/dependency_links.txt
stf_selector.egg-info/entry_points.txt
stf_selector.egg-info/not-zip-safe
stf_selector.egg-info/requires.txt
stf_selector.egg-info/top_level.txt
tests/__init__.py
tests/conftest.py
tests/test_stf_selector.py