Metadata-Version: 1.1
Name: stf-selector
Version: 0.1.0
Summary: stf devices stf_selector
Home-page: https://github.com/wliu_intern/stf_selector
Author: Juan Liu
Author-email: littlewei_liu@163.com
License: Apache Software License 2.0
Keywords: stf_selector
Platform: UNKNOWN
Classifier: Development Status :: 2 - Pre-Alpha
Classifier: Intended Audience :: Developers
Classifier: License :: OSI Approved :: Apache Software License
Classifier: Natural Language :: English
Classifier: Programming Language :: Python :: 2
Classifier: Programming Language :: Python :: 2.6
Classifier: Programming Language :: Python :: 2.7
Classifier: Programming Language :: Python :: 3
Classifier: Programming Language :: Python :: 3.3
Classifier: Programming Language :: Python :: 3.4
Classifier: Programming Language :: Python :: 3.5
